{
  "id": "eiken3",
  "level": 1,
  "label": "📚 英検3級 単語・熟語",
  "description": "実用英語技能検定3級レベルの重要単語・熟語クイズ。動詞・名詞・形容詞・副詞・会話表現・重要熟語の10セット（100語）で中学卒業程度の頻出語彙を反復練習できる",
  "tests": [
    {
      "id": 1,
      "title": "動詞編①：3級頻出の基本動詞をマスターしよう",
      "type": "Verbs 1",
      "emoji": "🏃",
      "subtitle": "3級頻出の基本動詞をマスターしよう",
      "questions": [
        {
          "scenario": "「prepare」の意味として最も適切なものは？",
          "choices": [
            "準備する、用意する",
            "片付ける",
            "捨てる",
            "忘れる"
          ],
          "correct": 0,
          "explanation": "prepareは「準備する、用意する」という意味です。例: prepare for the exam（試験の準備をする）",
          "type": "choice"
        },
        {
          "scenario": "「suggest」の意味として最も適切なものは？",
          "choices": [
            "提案する、示唆する",
            "命令する",
            "拒否する",
            "質問する"
          ],
          "correct": 0,
          "explanation": "suggestは「提案する、示唆する」という意味です。例: suggest a plan（計画を提案する）",
          "type": "choice"
        },
        {
          "scenario": "「suppose」の意味として最も適切なものは？",
          "choices": [
            "推測する、思う",
            "確信する",
            "証明する",
            "否定する"
          ],
          "correct": 0,
          "explanation": "supposeは「推測する、〜だと思う」という意味です。例: I suppose so.（そうだと思います。）",
          "type": "choice"
        },
        {
          "scenario": "「advise」の意味として最も適切なものは？",
          "choices": [
            "忠告する、アドバイスする",
            "命令する",
            "反対する",
            "尋ねる"
          ],
          "correct": 0,
          "explanation": "adviseは「忠告する、アドバイスする」という意味の動詞です。名詞形はadvice（助言、不可算名詞）です。",
          "type": "choice"
        },
        {
          "scenario": "「affect」の意味として最も適切なものは？",
          "choices": [
            "影響を与える、作用する",
            "結果をもたらす",
            "避ける",
            "保護する"
          ],
          "correct": 0,
          "explanation": "affectは「〜に影響を与える、作用する」という意味の動詞です。名詞形はeffect（効果、影響）です。",
          "type": "choice"
        },
        {
          "scenario": "「afford」の意味として最も適切なものは？",
          "choices": [
            "〜する（経済的・時間的）余裕がある",
            "支払う",
            "浪費する",
            "購入する"
          ],
          "correct": 0,
          "explanation": "affordは can を伴って「〜する余裕がある、〜を買う余裕がある」という意味の動詞です。",
          "type": "choice"
        },
        {
          "scenario": "「announce」の意味として最も適切なものは？",
          "choices": [
            "発表する、アナウンスする、告知する",
            "隠す",
            "沈黙する",
            "否定する"
          ],
          "correct": 0,
          "explanation": "announceは公式に情報を「発表する、告知する」という意味の動詞です。アナウンサーは announcer です。",
          "type": "choice"
        },
        {
          "scenario": "「apologize」の意味として最も適切なものは？",
          "choices": [
            "謝る、謝罪する",
            "許す",
            "非難する",
            "文句を言う"
          ],
          "correct": 0,
          "explanation": "apologizeは「謝る、謝罪する（apologize to 人 for 事柄）」という意味の動詞です。名詞形はapology（謝罪）です。",
          "type": "choice"
        },
        {
          "scenario": "「assist」の意味として最も適切なものは？",
          "choices": [
            "手伝う、援助する",
            "邪魔する",
            "支配する",
            "命令する"
          ],
          "correct": 0,
          "explanation": "assistは仕事や活動を「手伝う、援助する」という意味の動詞です。アシスタントは assistant です。",
          "type": "choice"
        },
        {
          "scenario": "「assume」の意味として最も適切なものは？",
          "choices": [
            "（証拠はないが）仮定する、思い込む",
            "証明する",
            "疑う",
            "否定する"
          ],
          "correct": 0,
          "explanation": "assumeは、はっきりした証拠がない中で「仮定する、思い込む、当然と思う」という意味の動詞です。",
          "type": "choice"
        }
      ]
    },
    {
      "id": 2,
      "title": "動詞編②：伝える・考える・感じるに関わる動詞",
      "type": "Verbs 2",
      "emoji": "💭",
      "subtitle": "伝える・考える・感じるに関わる動詞",
      "questions": [
        {
          "scenario": "「attract」の意味として最も適切なものは？",
          "choices": [
            "引きつける、魅了する",
            "遠ざける",
            "拒絶する",
            "攻撃する"
          ],
          "correct": 0,
          "explanation": "attractは人や注目を「引きつける、魅了する」という意味の動詞です。観光名所は attraction です。",
          "type": "choice"
        },
        {
          "scenario": "「bite」の意味として最も適切なものは？",
          "choices": [
            "（歯で）噛む、虫が刺す、噛むこと、一口",
            "投げる",
            "拾う",
            "隠す"
          ],
          "correct": 0,
          "explanation": "biteは「（歯で）噛む」または蚊などが「刺す」という動詞、また「噛むこと、一口」という名詞の意味もあります。過去形は bit、過去分詞は bitten です。",
          "type": "choice"
        },
        {
          "scenario": "「blame」の意味として最も適切なものは？",
          "choices": [
            "〜のせいにする、非難する",
            "褒める",
            "許す",
            "感謝する"
          ],
          "correct": 0,
          "explanation": "blameは過失などについて「〜のせいにする、非難する（blame A for B）」という意味の動詞です。",
          "type": "choice"
        },
        {
          "scenario": "「bother」の意味として最も適切なものは？",
          "choices": [
            "悩ます、困らせる、わざわざ〜する",
            "助ける",
            "喜ばせる",
            "無視する"
          ],
          "correct": 0,
          "explanation": "botherは「〜を悩ます、困らせる」または否定・疑問文で「わざわざ〜する」という意味の動詞です。",
          "type": "choice"
        },
        {
          "scenario": "「bow」の意味として最も適切なものは？",
          "choices": [
            "お辞儀する、屈服する、お辞儀、弓",
            "握手する",
            "手を振る",
            "跳ぶ"
          ],
          "correct": 0,
          "explanation": "bowは挨拶などで「お辞儀する」という動詞、また「お辞儀」や「弓」という名詞の意味もあります。",
          "type": "choice"
        },
        {
          "scenario": "「capture」の意味として最も適切なものは？",
          "choices": [
            "捕らえる、捕獲する、獲得する",
            "解放する",
            "捨てる",
            "破壊する"
          ],
          "correct": 0,
          "explanation": "captureは動物や犯人を「捕らえる、捕獲する」または画像などを「取り込む」という意味の動詞です。",
          "type": "choice"
        },
        {
          "scenario": "「cheer」の意味として最も適切なものは？",
          "choices": [
            "元気づける、歓声をあげる、歓声、声援",
            "悲しむ",
            "非難する",
            "無視する"
          ],
          "correct": 0,
          "explanation": "cheerは「元気づける（cheer up）」または「歓声をあげる、応援する」という動詞・名詞です。",
          "type": "choice"
        },
        {
          "scenario": "「command」の意味として最も適切なものは？",
          "choices": [
            "命令する、見渡す、命令、指揮",
            "従う",
            "頼む",
            "提案する"
          ],
          "correct": 0,
          "explanation": "commandは権限を持って「命令する、指揮する」という動詞・名詞です。例: command the troops（部隊を指揮する）",
          "type": "choice"
        },
        {
          "scenario": "「confuse」の意味として最も適切なものは？",
          "choices": [
            "混乱させる、混同する",
            "整理する",
            "理解する",
            "説明する"
          ],
          "correct": 0,
          "explanation": "confuseは人を「混乱させる」または区別できずに「混同する（confuse A with B）」という意味の動詞です。",
          "type": "choice"
        },
        {
          "scenario": "「consider」の意味として最も適切なものは？",
          "choices": [
            "よく考える、考慮する、みなす",
            "無視する",
            "決定する",
            "忘れる"
          ],
          "correct": 0,
          "explanation": "considerは「〜をよく考える、考慮する」または「〜とみなす」という意味の動詞です。名詞形はconsideration（考慮）です。例: consider the problem（問題をよく考える）",
          "type": "choice"
        }
      ]
    },
    {
      "id": 3,
      "title": "動詞編③：日常生活でよく使う動作動詞をチェック",
      "type": "Verbs 3",
      "emoji": "🔨",
      "subtitle": "日常生活でよく使う動作動詞をチェック",
      "questions": [
        {
          "scenario": "「convert」の意味として最も適切なものは？",
          "choices": [
            "変換する、変える、改宗させる",
            "維持する",
            "破壊する",
            "隠す"
          ],
          "correct": 0,
          "explanation": "convertは形や用途、通貨などを「変換する、変える」という意味の動詞です。例: convert dollars into yen（ドルを円に換算する）",
          "type": "choice"
        },
        {
          "scenario": "「convey」の意味として最も適切なものは？",
          "choices": [
            "（情報や思想などを）伝える、運ぶ",
            "隠す",
            "拒絶する",
            "受け取る"
          ],
          "correct": 0,
          "explanation": "conveyは言葉や態度で「（情報・感情などを）伝える」または「運ぶ」という意味の動詞です。例: convey my thanks（感謝の気持ちを伝える）",
          "type": "choice"
        },
        {
          "scenario": "「cope」の意味として最も適切なものは？",
          "choices": [
            "（問題などに）うまく対処する、処理する",
            "あきらめる",
            "悪化させる",
            "避ける"
          ],
          "correct": 0,
          "explanation": "copeは cope with 〜 の形で「（問題や困難に）うまく対処する、処理する」という意味の動詞です。deal with に似ています。",
          "type": "choice"
        },
        {
          "scenario": "「damage」の意味として最も適切なものは？",
          "choices": [
            "損害を与える、傷つける、損害、被害",
            "修理する",
            "保護する",
            "改善する"
          ],
          "correct": 0,
          "explanation": "damageは「（物や体に）損害を与える、傷つける」という動詞、また「損害、被害（不可算名詞）」という名詞の意味もあります。",
          "type": "choice"
        },
        {
          "scenario": "「decorate」の意味として最も適切なものは？",
          "choices": [
            "装飾する、飾る",
            "片付ける",
            "壊す",
            "汚す"
          ],
          "correct": 0,
          "explanation": "decorateは部屋やケーキなどを「装飾する、飾る」という意味の動詞です。名詞形はdecorationです。例: decorate the room with flowers（花で部屋を飾る）",
          "type": "choice"
        },
        {
          "scenario": "「defeat」の意味として最も適切なものは？",
          "choices": [
            "打ち負かす、破る、敗北",
            "負ける",
            "降伏する",
            "助ける"
          ],
          "correct": 0,
          "explanation": "defeatは試合や戦争で相手を「打ち負かす、破る」という動詞、また「敗北」という名詞の意味もあります。対義語は surrender などです。",
          "type": "choice"
        },
        {
          "scenario": "「defend」の意味として最も適切なものは？",
          "choices": [
            "守る、防御する、弁護する",
            "攻撃する",
            "降伏する",
            "非難する"
          ],
          "correct": 0,
          "explanation": "defendは敵や批判から「守る、防御する、弁護する」という意味の動詞です。対義語はattack（攻撃する）です。ディフェンスの動詞形です。",
          "type": "choice"
        },
        {
          "scenario": "「delay」の意味として最も適切なものは？",
          "choices": [
            "遅らせる、延期する、遅れ、遅延",
            "急がせる",
            "開始する",
            "完了する"
          ],
          "correct": 0,
          "explanation": "delayは「〜を遅らせる、延期する」という動詞、また「遅れ、遅延」という名詞でもあります。例: without delay（遅滞なく、すぐに）",
          "type": "choice"
        },
        {
          "scenario": "「demand」の意味として最も適切なものは？",
          "choices": [
            "強く要求する、請求する、需要、要求",
            "提案する",
            "譲歩する",
            "拒絶する"
          ],
          "correct": 0,
          "explanation": "demandは権利として「強く要求する」という動詞・名詞です。経済用語で supply（供給）と demand（仕様）の対比が有名です。",
          "type": "choice"
        },
        {
          "scenario": "「deny」の意味として最も適切なものは？",
          "choices": [
            "否定する、拒む",
            "認める",
            "主張する",
            "説明する"
          ],
          "correct": 0,
          "explanation": "denyは容疑や事実を「否定する、そんなことはないと言う」という意味の動詞です。対義語はadmit（認める）です。名詞形はdenialです。",
          "type": "choice"
        }
      ]
    },
    {
      "id": 4,
      "title": "動詞編④：会話や文章で頻出の重要動詞",
      "type": "Verbs 4",
      "emoji": "📝",
      "subtitle": "会話や文章で頻出の重要動詞",
      "questions": [
        {
          "scenario": "「depart」の意味として最も適切なものは？",
          "choices": [
            "出発する、旅立つ",
            "到着する",
            "留まる",
            "帰国する"
          ],
          "correct": 0,
          "explanation": "departは「（次の目的地に向けて）出発する、旅立つ」という意味の動詞です。名詞形はdeparture（出発）です。対義語はarriveです。",
          "type": "choice"
        },
        {
          "scenario": "「deserve」の意味として最も適切なものは？",
          "choices": [
            "（賞や罰などに）値する、〜する価値がある",
            "不足している",
            "避ける",
            "拒絶する"
          ],
          "correct": 0,
          "explanation": "deserveは、行動の結果として「〜に値する、〜する資格がある」という意味の動詞です。例: deserve to win（勝つ価値がある）",
          "type": "choice"
        },
        {
          "scenario": "「detect」の意味として最も適切なものは？",
          "choices": [
            "探知する、検出する、見つける",
            "隠す",
            "破壊する",
            "無視する"
          ],
          "correct": 0,
          "explanation": "detectは機械などでかすかな兆候やウイルスを「探知する、検出する」という意味の動詞です。探偵は detective です。",
          "type": "choice"
        },
        {
          "scenario": "「determine」の意味として最も適切なものは？",
          "choices": [
            "決定する、決意する、特定する",
            "迷う",
            "変更する",
            "提案する"
          ],
          "correct": 0,
          "explanation": "determineは事実や方針を「決定する」または「〜を決意する（be determined to do）」という意味の動詞です。名詞形はdeterminationです。",
          "type": "choice"
        },
        {
          "scenario": "「differ」の意味として最も適切なものは？",
          "choices": [
            "異なる、意見が合わない",
            "一致する",
            "似ている",
            "競争する"
          ],
          "correct": 0,
          "explanation": "differは性質などが「異なる、違っている（differ from 〜）」という意味の動詞です。形容詞differentの動詞形です。意見が合わないという意味も持ちます。",
          "type": "choice"
        },
        {
          "scenario": "「divide」の意味として最も適切なものは？",
          "choices": [
            "分ける、分割する、分類する",
            "混ぜる",
            "集める",
            "拡大する"
          ],
          "correct": 0,
          "explanation": "divideは「（いくつかの部分に）分ける、分割する」という意味の動詞です。名詞形はdivisionです。例: divide the cake into four（ケーキを4つに分ける）",
          "type": "choice"
        },
        {
          "scenario": "「donate」の意味として最も適切なものは？",
          "choices": [
            "寄付する、提供する",
            "購入する",
            "集める",
            "捨てる"
          ],
          "correct": 0,
          "explanation": "donateはお金や物、血液などを「寄付する、提供する」という意味の動詞です。名詞形はdonation（寄付）です。ドナーは donor です。",
          "type": "choice"
        },
        {
          "scenario": "「drag」Meaning?",
          "choices": [
            "引きずる、引っ張る、引きずること",
            "押す",
            "持ち上げる",
            "投げる"
          ],
          "correct": 0,
          "explanation": "dragは「（重いものを床などに沿って）引きずる、引っ張る」という意味の動詞です。パソコン操作の「ドラッグ」のことです。例: drag a bag（バッグを引きずる）",
          "type": "choice"
        },
        {
          "scenario": "「earn」の意味として最も適切なものは？",
          "choices": [
            "（お金などを）稼ぐ、得る、博する",
            "支払う",
            "寄付する",
            "失う"
          ],
          "correct": 0,
          "explanation": "earnは労働の対価として「（お金・生活費などを）稼ぐ」、または名声などを「得る」という意味の動詞です。例: earn money（お金を稼ぐ）",
          "type": "choice"
        },
        {
          "scenario": "「educate」の意味として最も適切なものは？",
          "choices": [
            "教育する、教える",
            "学ぶ",
            "保護する",
            "罰する"
          ],
          "correct": 0,
          "explanation": "educateは「教育する、教える」という意味の動詞です。名詞形はeducation（教育）です。例: educate children（子供たちを教育する）",
          "type": "choice"
        }
      ]
    },
    {
      "id": 5,
      "title": "動詞編⑤：行動や変化を表す動詞を身につけよう",
      "type": "Verbs 5",
      "emoji": "🎯",
      "subtitle": "行動や変化を表す動詞を身につけよう",
      "questions": [
        {
          "scenario": "「elect」の意味として最も適切なものは？",
          "choices": [
            "（選挙で）選出する、選ぶ",
            "投票する",
            "任命する",
            "辞職する"
          ],
          "correct": 0,
          "explanation": "electは投票や選挙によって「選出する、選ぶ」という意味の動詞です。名詞形はelection（選挙）です。例: elect a president（大統領を選出する）",
          "type": "choice"
        },
        {
          "scenario": "「embarrass」の意味として最も適切なものは？",
          "choices": [
            "恥ずかしがらせる、困惑させる",
            "喜ばせる",
            "安心させる",
            "怒らせる"
          ],
          "correct": 0,
          "explanation": "embarrassは人を「恥ずかしがらせる、決まりの悪い思いをさせる」という意味の動詞です。形容詞は embarrassed です。例: embarrass him（彼を困惑させる）",
          "type": "choice"
        },
        {
          "scenario": "「emerge」の意味として最も適切なものは？",
          "choices": [
            "現れる、出現する、浮かび上がる",
            "消える",
            "沈む",
            "移動する"
          ],
          "correct": 0,
          "explanation": "emergeは暗闇や水の中から「現れる、出現する」または問題が「浮かび上がる」という意味の動詞です。名詞形はemergenceです。",
          "type": "choice"
        },
        {
          "scenario": "「employ」の意味として最も適切なものは？",
          "choices": [
            "雇う、用いる",
            "解雇する",
            "働く",
            "指示する"
          ],
          "correct": 0,
          "explanation": "employは「（人を）雇う」または方法などを「用いる」という意味の動詞です。雇用主は employer、従業員は employee です。名詞形はemploymentです。",
          "type": "choice"
        },
        {
          "scenario": "「encounter」の意味として最も適切なものは？",
          "choices": [
            "遭遇する、偶然出会う、遭遇、衝突",
            "避ける",
            "約束する",
            "追いかける"
          ],
          "correct": 0,
          "explanation": "encounterは困難や未知の人に「偶然出会う、遭遇する」という動詞・名詞です。meet by chanceとほぼ同じです。例: encounter a problem（問題に遭遇する）",
          "type": "choice"
        },
        {
          "scenario": "「endure」の意味として最も適切なものは？",
          "choices": [
            "（苦痛などに）耐える、辛抱する、持ちこたえる",
            "あきらめる",
            "楽しむ",
            "怒る"
          ],
          "correct": 0,
          "explanation": "endureは苦痛や困難に「耐える、辛抱する」という意味の動詞です。bear や stand に似ています。名詞形はendurance（耐久力）です。",
          "type": "choice"
        },
        {
          "scenario": "「ensure」の意味として最も適切なものは？",
          "choices": [
            "確実にする、保証する、確保する",
            "疑う",
            "否定する",
            "無視する"
          ],
          "correct": 0,
          "explanation": "ensureは「確実にする、保証する」という意味の動詞です。sure（確実な）から派生しています。例: ensure safety（安全を確保する）",
          "type": "choice"
        },
        {
          "scenario": "「entertain」の意味として最も適切なものは？",
          "choices": [
            "楽しませる、もてなす",
            "退屈させる",
            "歓迎する",
            "批判する"
          ],
          "correct": 0,
          "explanation": "entertainは映画やショーで観客を「楽しませる」または客を「もてなす」という意味の動詞です。名詞形はentertainmentです。",
          "type": "choice"
        },
        {
          "scenario": "「envy」の意味として最も適切なものは？",
          "choices": [
            "うらやむ、ねたむ、うらやみ、裂け目",
            "誇りに思う",
            "嫌う",
            "同情する"
          ],
          "correct": 0,
          "explanation": "envyは他人の幸運や所有物を「うらやむ、ねたむ」という動詞・名詞です。例: envy his success（彼の成功をうらやむ）",
          "type": "choice"
        },
        {
          "scenario": "「establish」の意味として最も適切なものは？",
          "choices": [
            "設立する、確立する、創立する",
            "破壊する",
            "廃止する",
            "売却する"
          ],
          "correct": 0,
          "explanation": "establishは学校や会社を「設立する」または関係を「確立する」という意味の動詞です。名詞形はestablishmentです。foundとほぼ同じです。",
          "type": "choice"
        }
      ]
    },
    {
      "id": 6,
      "title": "動詞編⑥：コミュニケーションに関わる動詞表現",
      "type": "Verbs 6",
      "emoji": "💪",
      "subtitle": "コミュニケーションに関わる動詞表現",
      "questions": [
        {
          "scenario": "「estimate」の意味として最も適切なものは？",
          "choices": [
            "見積もる、推定する、見積もり、評価",
            "計算する",
            "決定する",
            "無視する"
          ],
          "correct": 0,
          "explanation": "estimateは費用や数量を「見積もる、推定する」という動詞・名詞です。例: estimate the cost（費用を見積もる）",
          "type": "choice"
        },
        {
          "scenario": "「exhibit」の意味として最も適切なものは？",
          "choices": [
            "展示する、展覧会に出品する、展示品",
            "隠す",
            "購入する",
            "印刷する"
          ],
          "correct": 0,
          "explanation": "exhibitは美術館などで作品を「展示する」という意味の動詞・名詞です。名詞形はexhibition（展覧会）です。例: exhibit paintings（絵画を展示する）",
          "type": "choice"
        },
        {
          "scenario": "「expand」の意味として最も適切なものは？",
          "choices": [
            "拡大する、広がる、拡張する",
            "縮小する",
            "閉じる",
            "停止する"
          ],
          "correct": 0,
          "explanation": "expandはビジネスや事業、気体などが「拡大する、広がる、膨張する」という意味の動詞です。名詞形はexpansionです。",
          "type": "choice"
        },
        {
          "scenario": "「fade」の意味として最も適切なものは？",
          "choices": [
            "（色が）あせる、（音が）消えていく、衰える",
            "現れる",
            "輝く",
            "高まる"
          ],
          "correct": 0,
          "explanation": "fadeは色や記憶が「あせる、薄れる」、または音や光が「徐々に消えていく（フェードアウト）」という意味の動詞です。",
          "type": "choice"
        },
        {
          "scenario": "「fear」の意味として最も適切なものは？",
          "choices": [
            "恐れる、怖がる、恐怖、心配",
            "立ち向かう",
            "好む",
            "驚く"
          ],
          "correct": 0,
          "explanation": "fearは「（危険などを）恐れる、怖がる」という動詞、また「恐怖、不安」という名詞でもあります。例: fear of dark（暗闇への恐怖）",
          "type": "choice"
        },
        {
          "scenario": "「fetch」の意味として最も適切なものは？",
          "choices": [
            "（行って）取ってくる、連れてくる",
            "持っていく",
            "投げる",
            "捨てる"
          ],
          "correct": 0,
          "explanation": "fetchは「（ある場所に行って物や人を）取ってくる、呼んでくる、連れてくる」という意味の動詞です。go and get とほぼ同じです。",
          "type": "choice"
        },
        {
          "scenario": "「float」の意味として最も適切なものは？",
          "choices": [
            "浮かぶ、漂う、浮き、浮き輪",
            "沈む",
            "泳ぐ",
            "流される"
          ],
          "correct": 0,
          "explanation": "floatは水面や空中に「浮かぶ、漂う」という動詞、また「浮き、浮き輪」という名詞の意味もあります。対義語は sink（沈む）です。",
          "type": "choice"
        },
        {
          "scenario": "「flow」の意味として最も適切なものは？",
          "choices": [
            "流れる、わき出る、流れ",
            "凍る",
            "注ぐ",
            "吹きつける"
          ],
          "correct": 0,
          "explanation": "flowは水や空気が「流れる、わき出る」という動詞、また「流れ」という名詞でもあります。例: flow of traffic（交通の流れ）",
          "type": "choice"
        },
        {
          "scenario": "「focus」の意味として最も適切なものは？",
          "choices": [
            "集中する、焦点を合わせる、焦点、中心",
            "ぼやける",
            "分散する",
            "避ける"
          ],
          "correct": 0,
          "explanation": "focusは focus on 〜 の形で「〜に集中する、焦点を合わせる」という動詞、また「焦点、中心」という名詞の意味もあります。",
          "type": "choice"
        },
        {
          "scenario": "「fold」の意味として最も適切なものは？",
          "choices": [
            "折る、折りたたむ、腕を組む",
            "開く",
            "破る",
            "切る"
          ],
          "correct": 0,
          "explanation": "foldは紙や服を「折る、折りたたむ」という意味の動詞です。腕や足を組む時にも使われます。対義語は unfold です。フォルダー（folder）の語源です。",
          "type": "choice"
        }
      ]
    },
    {
      "id": 7,
      "title": "動詞編⑦：判断・決定に関わる動詞をおさえよう",
      "type": "Verbs 7",
      "emoji": "🗣️",
      "subtitle": "判断・決定に関わる動詞をおさえよう",
      "questions": [
        {
          "scenario": "「force」の意味として最も適切なものは？",
          "choices": [
            "強いる、強制する、力、暴力",
            "許す",
            "頼む",
            "説得する"
          ],
          "correct": 0,
          "explanation": "forceは force 人 to do で「人に無理やり〜させる、強いる」という動詞、また物理的・社会的な「力、暴力」という名詞の意味もあります。",
          "type": "choice"
        },
        {
          "scenario": "「forecast」の意味として最も適切なものは？",
          "choices": [
            "予報する、予測する、予報、予測",
            "思い出す",
            "過去を振り返る",
            "放送する"
          ],
          "correct": 0,
          "explanation": "forecastは天気や経済を「予報する、予測する」という動詞、また「予報、予測」という名詞でもあります。例: weather forecast（天気予報）",
          "type": "choice"
        },
        {
          "scenario": "「frighten」の意味として最も適切なものは？",
          "choices": [
            "怖がらせる、ゾッとさせる",
            "喜ばせる",
            "驚かせる",
            "怒らせる"
          ],
          "correct": 0,
          "explanation": "frightenは「（一時的に）怖がらせる、ゾッとさせる」という意味の動詞です。scareやterrifyに似ています。形容詞は frightened（怯えた）です。",
          "type": "choice"
        },
        {
          "scenario": "「gaze」の意味として最も適切なものは？",
          "choices": [
            "（見とれて）見つめる、凝視する、凝視",
            "一瞥する",
            "目をそらす",
            "無視する"
          ],
          "correct": 0,
          "explanation": "gazeは、興味や驚きを持って「（じっと）見つめる、凝視する」という動詞・名詞です。stare（にらみつける）より好意的なニュアンスが多いです。",
          "type": "choice"
        },
        {
          "scenario": "「guarantee」の意味として最も適切なものは？",
          "choices": [
            "保証する、請け合う、保証、保証書",
            "疑う",
            "否定する",
            "壊す"
          ],
          "correct": 0,
          "explanation": "guaranteeは品質や権利を「保証する、約束する」という動詞・名詞です。電化製品の保証書は warranty とも言います。",
          "type": "choice"
        },
        {
          "scenario": "「hang」の意味として最も適切なものは？",
          "choices": [
            "掛ける、ぶら下がる、絞首刑にする",
            "落とす",
            "投げる",
            "拾う"
          ],
          "correct": 0,
          "explanation": "hangは「（壁などに）掛ける、ぶら下がる」という意味の動詞です。過去形・過去分詞は hung（絞首刑の意味では hanged）です。",
          "type": "choice"
        },
        {
          "scenario": "「harm」の意味として最も適切なものは？",
          "choices": [
            "害する、傷つける、害、損害",
            "保護する",
            "治療する",
            "助ける"
          ],
          "correct": 0,
          "explanation": "harmは「（健康や評判などを）害する、傷つける」という動詞、また「害、悪影響」という名詞の意味もあります。形容詞はharmful（有害な）です。",
          "type": "choice"
        },
        {
          "scenario": "「heal」の意味として最も適切なものは？",
          "choices": [
            "（傷などが）治る、癒やす、治療する",
            "痛む",
            "悪化する",
            "傷つける"
          ],
          "correct": 0,
          "explanation": "healはケガや心の痛みが「治る、癒える」または「治療する」という意味の動詞です。cure（病気を治す）に似ています。ヒーリング（healing）の動詞形です。",
          "type": "choice"
        },
        {
          "scenario": "「hesitate」の意味として最も適切なものは？",
          "choices": [
            "ためらう、躊躇する",
            "決心する",
            "急ぐ",
            "拒絶する"
          ],
          "correct": 0,
          "explanation": "hesitateは不安などで「ためらう、躊躇する」という意味の動詞です。名詞形はhesitationです。例: Don't hesitate to ask.（遠慮なく尋ねてください。）",
          "type": "choice"
        },
        {
          "scenario": "「hunt」の意味として最も適切なものは？",
          "choices": [
            "狩りをする、捜し求める、狩り",
            "逃げる",
            "隠す",
            "殺す"
          ],
          "correct": 0,
          "explanation": "huntは獲物を「狩る、狩猟する」または探し物を「捜し求める（hunt for 〜）」という動詞・名詞です。例: job hunting（就職活動）",
          "type": "choice"
        }
      ]
    },
    {
      "id": 8,
      "title": "動詞編⑧：生活のさまざまな場面で使う動詞",
      "type": "Verbs 8",
      "emoji": "🤝",
      "subtitle": "生活のさまざまな場面で使う動詞",
      "questions": [
        {
          "scenario": "「identify」の意味として最も適切なものは？",
          "choices": [
            "（本人・同一物だと）特定する、確認する、同一視する",
            "疑う",
            "否定する",
            "隠す"
          ],
          "correct": 0,
          "explanation": "identifyは「（人や物をだれ・何であるか）特定する、確認する」という意味の動詞です。名詞形はidentification（ID、身分証明）です。例: identify the body（身元を確認する）",
          "type": "choice"
        },
        {
          "scenario": "「illustrate」の意味として最も適切なものは？",
          "choices": [
            "説明する、図解する、挿絵を入れる",
            "描く",
            "文章を書く",
            "読む"
          ],
          "correct": 0,
          "explanation": "illustrateは図や例を用いて「説明する、図解する」または本に「挿絵を入れる」という意味の動詞です。イラストは illustration です。",
          "type": "choice"
        },
        {
          "scenario": "「imitate」の意味として最も適切なものは？",
          "choices": [
            "模倣する、真似る、まねる",
            "創造する",
            "無視する",
            "嫌う"
          ],
          "correct": 0,
          "explanation": "imitateは動作や声を「模倣する、真似る」という意味の動詞です。コピーすることです。名詞形はimitation（模倣、模造品）です。",
          "type": "choice"
        },
        {
          "scenario": "「imply」の意味として最も適切なものは？",
          "choices": [
            "暗に示す、ほのめかす、含む",
            "明確に述べる",
            "否定する",
            "隠す"
          ],
          "correct": 0,
          "explanation": "implyは言葉の裏に「暗に示す、ほのめかす、言外に含む」という意味の動詞です。名詞形はimplicationです。対義語は express です。",
          "type": "choice"
        },
        {
          "scenario": "「import」の意味として最も適切なものは？",
          "choices": [
            "輸入する、導入する、輸入、輸入品",
            "輸出する",
            "販売する",
            "運ぶ"
          ],
          "correct": 0,
          "explanation": "importは「（外国から商品を）輸入する」という動詞・名詞です。im-（中に）+ port（港）です。対義語は export（輸出する）です。",
          "type": "choice"
        },
        {
          "scenario": "「impress」の意味として最も適切なものは？",
          "choices": [
            "感銘を与える、好印象を与える、感銘",
            "失望させる",
            "怒らせる",
            "無視する"
          ],
          "correct": 0,
          "explanation": "impressは「（人に）感銘を与える、強い印象を与える」という意味の動詞です。名詞形はimpression（印象）です。例: impress the interviewer（面接官に好印象を与える）",
          "type": "choice"
        },
        {
          "scenario": "「indicate」の意味として最も適切なものは？",
          "choices": [
            "指し示す、示す、表す",
            "隠す",
            "否定する",
            "避ける"
          ],
          "correct": 0,
          "explanation": "indicateは針や数値が「指し示す、表す、示す」という意味の動詞です。例: indicate a change（変化を示す）",
          "type": "choice"
        },
        {
          "scenario": "「insist」の意味として最も適切なものは？",
          "choices": [
            "強く主張する、言い張る",
            "譲歩する",
            "疑う",
            "黙る"
          ],
          "correct": 0,
          "explanation": "insistは反論されても「強く主張する、言い張る（insist on 〜 / insist that 〜）」という意味の動詞です。名詞形はinsistenceです。",
          "type": "choice"
        },
        {
          "scenario": "「inspect」の意味として最も適切なものは？",
          "choices": [
            "検査する、点検する、視察する",
            "無視する",
            "破壊する",
            "使用する"
          ],
          "correct": 0,
          "explanation": "inspectは欠陥などがないか「（詳しく）検査する、点検する、視察する」という意味の動詞です。検査官は inspector です。examineに似ています。",
          "type": "choice"
        },
        {
          "scenario": "「inspire」の意味として最も適切なものは？",
          "choices": [
            "奮い立たせる、ひらめきを与える",
            "落胆させる",
            "怒らせる",
            "邪魔する"
          ],
          "correct": 0,
          "explanation": "inspireは人を「奮い立たせる、創作意欲やひらめきを与える」という意味の動詞です。名詞形はinspiration（インスピレーション）です。",
          "type": "choice"
        }
      ]
    },
    {
      "id": 9,
      "title": "動詞編⑨：対人関係やビジネスに役立つ動詞",
      "type": "Verbs 9",
      "emoji": "🔄",
      "subtitle": "対人関係やビジネスに役立つ動詞",
      "questions": [
        {
          "scenario": "「insult」の意味として最も適切なものは？",
          "choices": [
            "侮辱する、無礼なことを言う、侮辱",
            "褒める",
            "謝罪する",
            "感謝する"
          ],
          "correct": 0,
          "explanation": "insultは「（言葉や態度で）侮辱する」という動詞、また「侮辱、無礼」という名詞でもあります。対義語はpraiseやcomplimentです。",
          "type": "choice"
        },
        {
          "scenario": "「intend」の意味として最も適切なものは？",
          "choices": [
            "意図する、〜するつもりである",
            "偶然行う",
            "あきらめる",
            "避ける"
          ],
          "correct": 0,
          "explanation": "intendは intend to do で「〜するつもりである、〜を意図する」という意味の動詞です。名詞形はintention（意図、目的）です。",
          "type": "choice"
        },
        {
          "scenario": "「interfere」の意味として最も適切なものは？",
          "choices": [
            "干渉する、邪魔する、お節介を焼く",
            "助ける",
            "無視する",
            "参加する"
          ],
          "correct": 0,
          "explanation": "interfereは interfere in/with 〜 で「（他人の事に）干渉する、邪魔する、お節介を焼く」という意味の動詞です。名詞形はinterferenceです。",
          "type": "choice"
        },
        {
          "scenario": "「interpret」の意味として最も適切なものは？",
          "choices": [
            "通訳する、解釈する、説明する",
            "聞く",
            "話す",
            "翻訳する"
          ],
          "correct": 0,
          "explanation": "interpretは言葉を「通訳する」または状況や夢を「解釈する」という意味の動詞です。通訳者は interpreter です。翻訳する（translate）とは区別されます。",
          "type": "choice"
        },
        {
          "scenario": "「interrupt」の意味として最も適切なものは？",
          "choices": [
            "中断する、遮る、邪魔をする",
            "続ける",
            "開始する",
            "助ける"
          ],
          "correct": 0,
          "explanation": "interruptは人の会話や作業を「中断する、途中で遮る、邪魔をする」という意味の動詞です。名詞形はinterruptionです。",
          "type": "choice"
        },
        {
          "scenario": "「judge」の意味として最も適切なものは？",
          "choices": [
            "判断する、裁く、裁判官、審査員",
            "従う",
            "迷う",
            "疑う"
          ],
          "correct": 0,
          "explanation": "judgeは善悪や勝敗を「判断する、裁く」という動詞、また「裁判官、審査員（ジャッジ）」という名詞でもあります。名詞形はjudgment（判断）です。",
          "type": "choice"
        },
        {
          "scenario": "「knit」の意味として最も適切なものは？",
          "choices": [
            "（毛糸などを）編む、編み物をする",
            "縫う",
            "織る",
            "切る"
          ],
          "correct": 0,
          "explanation": "knitは毛糸などでセーターなどを「編む、編み物をする」という意味の動詞です。例: knit a sweater（セーターを編む）",
          "type": "choice"
        },
        {
          "scenario": "「lack」の意味として最も適切なものは？",
          "choices": [
            "〜が不足している、欠いている、不足、欠乏",
            "十分にある",
            "必要とする",
            "余っている"
          ],
          "correct": 0,
          "explanation": "lackは必要なものが「不足している、欠いている」という動詞、また「不足、欠乏」という名詞の意味もあります。例: lack of sleep（睡眠不足）",
          "type": "choice"
        },
        {
          "scenario": "「last (動詞)」の意味として最も適切なものは？",
          "choices": [
            "（特定の時間）続く、持ちこたえる",
            "終わる",
            "始まる",
            "遅れる"
          ],
          "correct": 0,
          "explanation": "lastは形容詞「最後の」のほかに、動詞として状態や命が「（一定期間）続く、長持ちする」という意味を持ちます。例: The meeting lasted for two hours.（会議は2時間続いた。）",
          "type": "choice"
        },
        {
          "scenario": "「lay」の意味として最も適切なものは？",
          "choices": [
            "横たえる、置く、（卵を）産む",
            "横たわる",
            "立ち上がる",
            "飛ぶ"
          ],
          "correct": 0,
          "explanation": "layは「〜を横たえる、置く」または鳥や魚が「卵を産む」という他動詞です。自動詞 lie（横たわる）の過去形 lay と混同しやすいので注意しましょう。過去・過去分詞は laid です。",
          "type": "choice"
        }
      ]
    },
    {
      "id": 10,
      "title": "動詞編⑩：3級の得点力を上げる重要動詞",
      "type": "Verbs 10",
      "emoji": "⚡",
      "subtitle": "3級の得点力を上げる重要動詞",
      "questions": [
        {
          "scenario": "「leap」の意味として最も適切なものは？",
          "choices": [
            "（大きく）跳ぶ、跳躍する、跳躍",
            "走る",
            "歩く",
            "這う"
          ],
          "correct": 0,
          "explanation": "leapは「（大きく）跳ぶ、跳躍する」という動詞・名詞です。jumpよりもダイナミックな跳躍を指すことが多いです。例: leap year（うるう年）",
          "type": "choice"
        },
        {
          "scenario": "「limit」の意味として最も適切なものは？",
          "choices": [
            "制限する、限定する、制限、極限",
            "拡大する",
            "解放する",
            "超える"
          ],
          "correct": 0,
          "explanation": "limitは数量や範囲を「制限する、限定する」という動詞、また「制限、限界、極限」という名詞の意味もあります。例: speed limit（速度制限）",
          "type": "choice"
        },
        {
          "scenario": "「lock」の意味として最も適切なものは？",
          "choices": [
            "鍵をかける、錠、ロック",
            "鍵を開ける",
            "壊す",
            "閉める"
          ],
          "correct": 0,
          "explanation": "lockはドアなどに「鍵をかける」という動詞、また「錠、ロック」という名詞の意味もあります。対義語は unlock です。",
          "type": "choice"
        },
        {
          "scenario": "「maintain」の意味として最も適切なものは？",
          "choices": [
            "維持する、整備する、主張する",
            "変更する",
            "あきらめる",
            "破壊する"
          ],
          "correct": 0,
          "explanation": "maintainは良好な状態や関係を「維持する、保つ」または機械を「整備する」という意味の動詞です。名詞形はmaintenanceです。",
          "type": "choice"
        },
        {
          "scenario": "「manufacture」の意味として最も適切なものは？",
          "choices": [
            "（工場で大規模に）製造する、生産する、製造、製品",
            "購入する",
            "設計する",
            "破壊する"
          ],
          "correct": 0,
          "explanation": "manufactureは工場などで「（大規模に）製造する、生産する」という動詞・名詞です。製造業者は manufacturer です。",
          "type": "choice"
        },
        {
          "scenario": "「measure」の意味として最も適切なものは？",
          "choices": [
            "測定する、測る、寸法、対策",
            "見積もる",
            "計算する",
            "推測する"
          ],
          "correct": 0,
          "explanation": "measureは長さや重さを「測定する、測る」という動詞、また「寸法」や「対策（measures）」という名詞の意味もあります。名詞形はmeasurementです。",
          "type": "choice"
        },
        {
          "scenario": "「mind」の意味として最も適切なものは？",
          "choices": [
            "（否定・疑問文で）気にする、嫌がる、心、精神",
            "好む",
            "無視する",
            "忘れる"
          ],
          "correct": 0,
          "explanation": "mindは「（嫌がって）気にする、嫌だと思う」という動詞、また「心、精神」という名詞の意味もあります。例: Do you mind if I open the window?（窓を開けてもいいですか？）",
          "type": "choice"
        },
        {
          "scenario": "「mislead」の意味として最も適切なものは？",
          "choices": [
            "誤解させる、見当違いな方向へ導く",
            "正しく導く",
            "説明する",
            "説得する"
          ],
          "correct": 0,
          "explanation": "misleadは誤った情報で人を「誤解させる、欺く」という意味の動詞です。lead に誤りを表す mis- がついた形です。形容詞は misleading（誤解を招くような）です。",
          "type": "choice"
        },
        {
          "scenario": "「modify」の意味として最も適切なものは？",
          "choices": [
            "（部分的に）修正する、変更する、修飾する",
            "完全に変える",
            "破壊する",
            "維持する"
          ],
          "correct": 0,
          "explanation": "modifyは計画やデザインをより良くするために「（部分的に）修正する、変更する」という意味の動詞です。文法で「修飾する」の意味もあります。",
          "type": "choice"
        },
        {
          "scenario": "「mount」の意味として最も適切なものは？",
          "choices": [
            "（山などに）登る、載せる、台座",
            "下りる",
            "歩く",
            "滑り落ちる"
          ],
          "correct": 0,
          "explanation": "mountは「（山や馬などに）登る」またはカメラなどを「（台座に）載せる、固定する」という意味の動詞です。名詞では「山（Mount Fujiなど）」を指します。",
          "type": "choice"
        }
      ]
    }
  ]
}
